azure/ai/personalizer/__init__.py
azure/ai/personalizer/_client.py
azure/ai/personalizer/_configuration.py
azure/ai/personalizer/_patch.py
azure/ai/personalizer/_serialization.py
azure/ai/personalizer/_vendor.py
azure/ai/personalizer/_version.py
azure/ai/personalizer/py.typed
azure/ai/personalizer/_operations/__init__.py
azure/ai/personalizer/_operations/_operations.py
azure/ai/personalizer/_operations/_patch.py
azure/ai/personalizer/aio/__init__.py
azure/ai/personalizer/aio/_client.py
azure/ai/personalizer/aio/_configuration.py
azure/ai/personalizer/aio/_patch.py
azure/ai/personalizer/aio/_vendor.py
azure/ai/personalizer/aio/_operations/__init__.py
azure/ai/personalizer/aio/_operations/_operations.py
azure/ai/personalizer/aio/_operations/_patch.py
azure_ai_personalizer-1.0.0b1.dist-info/LICENSE
azure_ai_personalizer-1.0.0b1.dist-info/METADATA
azure_ai_personalizer-1.0.0b1.dist-info/WHEEL
azure_ai_personalizer-1.0.0b1.dist-info/top_level.txt
azure_ai_personalizer-1.0.0b1.dist-info/RECORD
