Metadata-Version: 2.1
Name: azure-ai-personalizer
Version: 1.0.0b1
Summary: Microsoft Azure Personalizer Client Library for Python
Home-page: https://github.com/Azure/azure-sdk-for-python
Author: Microsoft Corporation
Author-email: azuresdkengsysadmins@microsoft.com
License: MIT License
Project-URL: Bug Reports, https://github.com/Azure/azure-sdk-for-python/issues
Project-URL: Source, https://github.com/Azure/azure-sdk-python
Keywords: azure,personalizer,cognitive services,reinforcement learning,contextual bandit
Classifier: Development Status :: 4 - Beta
Classifier: Programming Language :: Python
Classifier: Programming Language :: Python :: 3 :: Only
Classifier: Programming Language :: Python :: 3
Classifier: Programming Language :: Python :: 3.7
Classifier: Programming Language :: Python :: 3.8
Classifier: Programming Language :: Python :: 3.9
Classifier: Programming Language :: Python :: 3.10
Classifier: Programming Language :: Python :: 3.11
Classifier: License :: OSI Approved :: MIT License
Requires-Python: >=3.7
License-File: LICENSE
Requires-Dist: azure-core (<2.0.0,>=1.24.0)
Requires-Dist: isodate (<1.0.0,>=0.6.1)
Requires-Dist: typing-extensions (>=4.0.1)
